signal_ICT_JenishDesai_92510133025/__init__.py
signal_ICT_JenishDesai_92510133025/operations.py
signal_ICT_JenishDesai_92510133025/trigonometric_signals.py
signal_ICT_JenishDesai_92510133025/unitary_signals.py
signal_ICT_JenishDesai_92510133025-0.1.0.dist-info/METADATA
signal_ICT_JenishDesai_92510133025-0.1.0.dist-info/WHEEL
signal_ICT_JenishDesai_92510133025-0.1.0.dist-info/top_level.txt
signal_ICT_JenishDesai_92510133025-0.1.0.dist-info/RECORD
