Metadata-Version: 2.1
Name: signal_ICT_JenishDesai_92510133025
Version: 0.1.0
Summary: Signal generation and operations package for LHC exam
Author: Jenish Desai
Author-email: example@example.com
License: MIT
Classifier: Programming Language :: Python :: 3
Classifier: License :: OSI Approved :: MIT License
Classifier: Operating System :: OS Independent
Requires-Python: >=3.8
